README.md
setup.py
pulumi_radarr/__init__.py
pulumi_radarr/_inputs.py
pulumi_radarr/_utilities.py
pulumi_radarr/provider.py
pulumi_radarr/pulumi-plugin.json
pulumi_radarr/py.typed
pulumi_radarr.egg-info/PKG-INFO
pulumi_radarr.egg-info/SOURCES.txt
pulumi_radarr.egg-info/dependency_links.txt
pulumi_radarr.egg-info/not-zip-safe
pulumi_radarr.egg-info/requires.txt
pulumi_radarr.egg-info/top_level.txt
pulumi_radarr/config/__init__.py
pulumi_radarr/config/outputs.py
pulumi_radarr/config/vars.py
pulumi_radarr/downloadclients/__init__.py
pulumi_radarr/downloadclients/aria2.py
pulumi_radarr/downloadclients/config.py
pulumi_radarr/downloadclients/deluge.py
pulumi_radarr/downloadclients/download_client.py
pulumi_radarr/downloadclients/flood.py
pulumi_radarr/downloadclients/freebox.py
pulumi_radarr/downloadclients/get_config.py
pulumi_radarr/downloadclients/get_download_client.py
pulumi_radarr/downloadclients/get_download_clients.py
pulumi_radarr/downloadclients/get_remote_path_mapping.py
pulumi_radarr/downloadclients/get_remote_path_mappings.py
pulumi_radarr/downloadclients/hadouken.py
pulumi_radarr/downloadclients/nzbget.py
pulumi_radarr/downloadclients/nzbvortex.py
pulumi_radarr/downloadclients/outputs.py
pulumi_radarr/downloadclients/pneumatic.py
pulumi_radarr/downloadclients/qbittorrent.py
pulumi_radarr/downloadclients/remote_path_mapping.py
pulumi_radarr/downloadclients/rtorrent.py
pulumi_radarr/downloadclients/sabnzbd.py
pulumi_radarr/downloadclients/torrent_blackhole.py
pulumi_radarr/downloadclients/torrent_download_station.py
pulumi_radarr/downloadclients/transmission.py
pulumi_radarr/downloadclients/usenet_blackhole.py
pulumi_radarr/downloadclients/usenet_download_station.py
pulumi_radarr/downloadclients/utorrent.py
pulumi_radarr/downloadclients/vuze.py
pulumi_radarr/importlists/__init__.py
pulumi_radarr/importlists/config.py
pulumi_radarr/importlists/couch_potato.py
pulumi_radarr/importlists/custom.py
pulumi_radarr/importlists/exclusion.py
pulumi_radarr/importlists/get_config.py
pulumi_radarr/importlists/get_exclusion.py
pulumi_radarr/importlists/get_exclusions.py
pulumi_radarr/importlists/get_import_list.py
pulumi_radarr/importlists/get_import_lists.py
