Metadata-Version: 2.1
Name: pulumi-radarr
Version: 2.0.0a2
Summary: A Pulumi package for creating and managing Radarr resources
Home-page: https://github.com/MaienM/pulumi-radarr
License: Apache-2.0
Project-URL: Repository, https://github.com/MaienM/pulumi-radarr
Keywords: pulumi radarr category/utility
Requires-Python: >=3.7
